ATKConnectModule.py
mcp_atk.py
mcp_atk-0.1.0.dist-info/METADATA
mcp_atk-0.1.0.dist-info/WHEEL
mcp_atk-0.1.0.dist-info/top_level.txt
mcp_atk-0.1.0.dist-info/RECORD
