Metadata-Version: 2.4
Name: mcp-atk
Version: 0.1.0
Summary: 运行atk仿真
Requires-Python: >=3.12
Requires-Dist: mcp[cli]>=1.11.0
